COPYING
ChangeLog
README
setup.cfg
setup.py
TracWikiTemplates.egg-info/PKG-INFO
TracWikiTemplates.egg-info/SOURCES.txt
TracWikiTemplates.egg-info/dependency_links.txt
TracWikiTemplates.egg-info/entry_points.txt
TracWikiTemplates.egg-info/pkg-info
TracWikiTemplates.egg-info/requires.txt
TracWikiTemplates.egg-info/top_level.txt
WikiTemplates/__init__.py
WikiTemplates/attachment.py
WikiTemplates/db_schema.py
WikiTemplates/errors.py
WikiTemplates/model.py
WikiTemplates/test.py
WikiTemplates/web_ui.py
WikiTemplates/DefaultTemplates/TemplatesIndex
WikiTemplates/htdocs/css/wikitemplates.css
WikiTemplates/htdocs/img/preview.png
WikiTemplates/htdocs/js/wikitemplates.js
WikiTemplates/macros/__init__.py
WikiTemplates/macros/image.py
WikiTemplates/macros/includes.py
WikiTemplates/macros/templates.py
WikiTemplates/templates/WikiTemplates.cs
WikiTemplates/upgrades/__init__.py
WikiTemplates/upgrades/db1.py