Metadata-Version: 1.0
Name: TracWikiTemplates
Version: 0.3.0
Summary: Trac Plugin to pre-format parts of the Wiki page using it
Home-page: http://wikitemplates.ufsoft.org
Author: Pedro Algarvio
Author-email: ufs@ufsoft.org
License: BSD
Download-URL: http://python.org/pypi/TracWikiTemplates
Platform: OS Independent - Anywhere Python and Trac >=0.10 is known to run.
Classifier: Development Status :: 5 - Production/Stable
Classifier: Environment :: Web Environment
Classifier: Intended Audience :: System Administrators
Classifier: License :: OSI Approved :: BSD License
Classifier: Operating System :: OS Independent
Classifier: Programming Language :: Python
Classifier: Topic :: Text Processing
Classifier: Topic :: Utilities
Classifier: Topic :: Internet :: WWW/HTTP
Classifier: Topic :: Internet :: WWW/HTTP :: Dynamic Content
